[1,["17ffb5948@6c48a"],["_textureSource"],["cc.SpriteFrame"],0,[[[{"name":"pisa","rect":{"x":215,"y":640,"width":222,"height":222},"offset":{"x":0,"y":3.5},"originalSize":{"width":222,"height":229},"rotated":false,"capInsets":[0,0,0,0],"packable":true}],[0],0,[0],[0],[0]],[[{"name":"panzi","rect":{"x":3,"y":3,"width":395,"height":397},"offset":{"x":0,"y":0},"originalSize":{"width":395,"height":397},"rotated":true,"capInsets":[0,0,0,0],"packable":true}],[0],0,[0],[0],[0]],[[{"name":"pingguo","rect":{"x":3,"y":404,"width":250,"height":230},"offset":{"x":-0.5,"y":0},"originalSize":{"width":251,"height":230},"rotated":false,"capInsets":[0,0,0,0],"packable":true}],[0],0,[0],[0],[0]],[[{"name":"bianbian","rect":{"x":3,"y":640,"width":225,"height":206},"offset":{"x":0.5,"y":-0.5},"originalSize":{"width":226,"height":207},"rotated":true,"capInsets":[0,0,0,0],"packable":true}],[0],0,[0],[0],[0]]]]
